enc_code/__init__.py
enc_code/inst.py
enc_code-0.0.0.dist-info/METADATA
enc_code-0.0.0.dist-info/WHEEL
enc_code-0.0.0.dist-info/top_level.txt
enc_code-0.0.0.dist-info/RECORD
